src/slave.v
module slave (
    input   wire    clk,
    input   wire    RSTn,
    input   wire    receive_en,
    input   wire    bus_valid,    
    input   wire[23:0] bus_data,
    output  wire    slave_ready    
);
    assign slave_ready = receive_en;
    reg [23:0]slave_buffer;
    always @(*) begin
        if(slave_ready && bus_valid)begin
            slave_buffer <= bus_data;
        end 
        else begin
            slave_buffer <= slave_buffer;
        end       
    end
    
endmodule //moduleName

src/bus.v
module bus(
        input	wire	clk			    ,
        input	wire	RSTn		    ,

        input	wire[23:0]master_data   ,
        input	wire	master_valid    ,
        output	wire	bus_ready	    ,

        input	wire	slave_ready     ,
        output	wire	bus_valid       ,
        output	wire[23:0] bus_data
    );

    reg  [23:0] DATA_BUFFER;
    reg buffer_full;
    reg slave_ready_d1;

    always @(posedge clk or negedge RSTn) begin
        if (!RSTn) begin
            slave_ready_d1 <= 1'd0;
        end
        else begin
            slave_ready_d1 <= slave_ready;
        end
    end

    //bus buffer refresh
    always @ (posedge clk or negedge RSTn) begin
        if (!RSTn) begin
            DATA_BUFFER <= 24'd0;
        end
        else if (master_valid && bus_ready && (!slave_ready) && (!buffer_full)) begin
            DATA_BUFFER <= master_data;
        end
        else begin
            DATA_BUFFER <= DATA_BUFFER;
        end
    end

    //bus buffer status
    always @(posedge clk or negedge RSTn) begin
        if (!RSTn)
            buffer_full <= 1'd0;
        else if (master_valid && (!slave_ready) && (!buffer_full))
            buffer_full <= 1'd1;
        else if (slave_ready == 1'd1)
            buffer_full <= 1'd0;
    end

    //bus ready
    assign bus_ready = (!buffer_full) || slave_ready_d1;

    //tx valid
    assign bus_valid = buffer_full || master_valid;

    //BUS_DATA
    assign bus_data = buffer_full ? DATA_BUFFER : master_data;


endmodule

src/master.v
module master(
        input	wire	clk			    ,
        input	wire	RSTn		    ,
        input   wire    master_en       ,

        output	wire	master_valid    ,
        input	wire	bus_ready	    ,

        output	reg[23:0] master_data
    );

    reg[2:0]cnt;
    assign master_valid = master_en;
    always @(posedge clk or negedge RSTn) begin
        if(!RSTn) begin
            cnt <= 3'b0;
        end
        else if(bus_ready && (cnt < 3'd5) && master_valid) begin
            cnt <= cnt +1'b1;
        end
        else if (bus_ready && (cnt == 3'd5) && master_valid) begin
            cnt <= 3'd0;
        end
        else begin
            cnt <= cnt;
        end
    end

    always @(*) begin
        case(cnt)
            3'd0: begin
                master_data <= 24'h001122;
            end
            3'd1: begin
                master_data <= 24'h112233;
            end
            3'd2: begin
                master_data <= 24'h223344;
            end
            3'd3: begin
                master_data <= 24'h334455;
            end
            3'd4: begin
                master_data <= 24'h445566;
            end
            3'd5: begin
                master_data <= 24'h556677;
            end
            default : begin
                master_data <= 24'hFFFFFF;
            end
        endcase
    end

endmodule

sim/sim_tb.v
`timescale 1ns/100ps
`include "../src/master.v"
`include "../src/bus.v"
`include "../src/slave.v"
module sim_tb();
    reg clk_50;
    reg RSTn;
    reg slave_en;
    reg master_en;

    wire [23:0]bus_data;
    wire bus_valid;
    wire bus_ready;

    wire [23:0]master_data;
    wire master_valid;
    wire slave_ready;

    master u_master(
               .clk	        	    (clk_50         ),
               .RSTn	            (RSTn           ),
               .master_en           (dut_master_en  ),
               .master_valid        (master_valid   ),
               .bus_ready	        (bus_ready      ),
               .master_data         (master_data    )
           );

    bus u_bus(
            //ports
            .clk          		( clk_50          	),
            .RSTn         		( RSTn         		),
            .master_data  		( master_data  	    ),
            .master_valid 		( master_valid 	    ),
            .bus_ready    		( bus_ready    		),
            .slave_ready  		( slave_ready  	    ),
            .bus_valid    		( bus_valid    		),
            .bus_data     		( bus_data     		)
        );
    slave u_slave(
              .clk              (clk_50             ),
              .RSTn             (RSTn               ),
              .receive_en       (dut_slave_en       ),
              .bus_valid        (bus_valid          ),
              .bus_data         (bus_data           ),
              .slave_ready      (slave_ready        )
          );

    assign #0.1 dut_master_en = master_en;
    assign #0.1 dut_slave_en = slave_en;


    always #10 clk_50 = ~clk_50;

    initial begin
        clk_50 = 1;
        RSTn = 0;
        slave_en = 0;
        master_en = 0;
        #20 RSTn = 1;
        #20 slave_en = 1;
        master_en = 1;
        #20 slave_en = 1;
        #20 slave_en = 0;
        master_en = 0;
        #20 slave_en = 0;
        #20 slave_en = 1;
        #20 slave_en = 0;
        master_en = 1;
        #20 slave_en = 1;
        #20 slave_en = 0;
        #20 slave_en = 1;
        #20 slave_en = 1;
        #20 slave_en = 0;

        #80 $finish;
    end

    initial begin
        $dumpfile("./sim_result/wave.vcd");
        $dumpvars(0, sim_tb);
    end


endmodule

sim_result/wave.vcd
$date
	Fri Jun 17 15:11:58 2022
$end
$version
	Icarus Verilog
$end
$timescale
	100ps
$end
$scope module sim_tb $end
$var wire 1 ! dut_master_en $end
$var wire 1 " dut_slave_en $end
$var wire 1 # slave_ready $end
$var wire 1 $ master_valid $end
$var wire 24 % master_data [23:0] $end
$var wire 1 & bus_valid $end
$var wire 1 ' bus_ready $end
$var wire 24 ( bus_data [23:0] $end
$var reg 1 ) RSTn $end
$var reg 1 * clk_50 $end
$var reg 1 + master_en $end
$var reg 1 , slave_en $end
$scope module u_bus $end
$var wire 1 ) RSTn $end
$var wire 1 ' bus_ready $end
$var wire 1 & bus_valid $end
$var wire 1 * clk $end
$var wire 1 # slave_ready $end
$var wire 1 $ master_valid $end
$var wire 24 - master_data [23:0] $end
$var wire 24 . bus_data [23:0] $end
$var reg 24 / DATA_BUFFER [23:0] $end
$var reg 1 0 buffer_full $end
$var reg 1 1 slave_ready_d1 $end
$upscope $end
$scope module u_master $end
$var wire 1 ) RSTn $end
$var wire 1 ' bus_ready $end
$var wire 1 * clk $end
$var wire 1 ! master_en $end
$var wire 1 $ master_valid $end
$var reg 3 2 cnt [2:0] $end
$var reg 24 3 master_data [23:0] $end
$upscope $end
$scope module u_slave $end
$var wire 1 ) RSTn $end
$var wire 24 4 bus_data [23:0] $end
$var wire 1 & bus_valid $end
$var wire 1 * clk $end
$var wire 1 " receive_en $end
$var wire 1 # slave_ready $end
$var reg 24 5 slave_buffer [23:0] $end
$upscope $end
$upscope $end
$enddefinitions $end
#0
$dumpvars
bx 5
b1000100100010 4
b1000100100010 3
b0 2
01
00
b0 /
b1000100100010 .
b1000100100010 -
0,
0+
1*
0)
b1000100100010 (
1'
x&
b1000100100010 %
x$
x#
x"
x!
$end
#1
0&
0$
0!
0#
0"
#100
0*
#200
1*
1)
#300
0*
#400
1*
1+
1,
#401
b1000100100010 5
1&
1$
1!
1#
1"
#500
0*
#600
b100010010001000110011 5
b100010010001000110011 (
b100010010001000110011 .
b100010010001000110011 4
b100010010001000110011 %
b100010010001000110011 -
b100010010001000110011 3
11
b1 2
1*
#700
0*
#800
b1000100011001101000100 5
b1000100011001101000100 (
b1000100011001101000100 .
b1000100011001101000100 4
b1000100011001101000100 %
b1000100011001101000100 -
b1000100011001101000100 3
b10 2
1*
0+
0,
#801
0&
0$
0!
0#
0"
#900
0*
#1000
01
1*
#1100
0*
#1200
1*
1,
#1201
1#
1"
#1300
0*
#1400
11
1*
1+
0,
#1401
1&
1$
1!
0#
0"
#1500
0*
#1600
b1100110100010001010101 %
b1100110100010001010101 -
b1100110100010001010101 3
0'
b11 2
01
b1000100011001101000100 /
10
1*
1,
#1601
1#
1"
#1700
0*
#1800
b1100110100010001010101 5
b1100110100010001010101 (
b1100110100010001010101 .
b1100110100010001010101 4
1'
00
11
1*
0,
#1801
0#
0"
#1900
0*
#2000
b10001000101010101100110 %
b10001000101010101100110 -
b10001000101010101100110 3
0'
b100 2
01
b1100110100010001010101 /
10
1*
1,
#2001
1#
1"
#2100
0*
#2200
b10001000101010101100110 5
b10001000101010101100110 (
b10001000101010101100110 .
b10001000101010101100110 4
1'
00
11
1*
#2300
0*
#2400
b10101010110011001110111 5
b10101010110011001110111 (
b10101010110011001110111 .
b10101010110011001110111 4
b10101010110011001110111 %
b10101010110011001110111 -
b10101010110011001110111 3
b101 2
1*
0,
#2401
0#
0"
#2500
0*
#2600
b1000100100010 %
b1000100100010 -
b1000100100010 3
0'
10
b10101010110011001110111 /
01
b0 2
1*
