src/spi_tx.v
//SPI data mode:00 ,speed:(50/24)MHz
//SCK keep 0 if idle; MOSI will be sampling in the rising edge of SCK
//note that, CS will keep high if no data need trans.
module spi_tx(
        input	wire	clk			,
        input	wire	RSTn		,

        input	wire[23:0]BUS_DATA	,
        input	wire	tx_valid	,
        output	wire	spi_ready	,

        output	wire	spi_cs		,
        output	reg		spi_clk		,
        output	wire	spi_data
    );
    localparam ST_IDLE = 2'b00;
    localparam ST_W    = 2'b01;
    localparam ST_WAIT = 2'b10;

    reg [1:0]cur_sta;
    reg [1:0]nxt_sta;
    reg [4:0]sclk_cnt;
    reg [4:0]data_cnt;
    reg [23:0]DATA_BUFFER;

    //bus handshake
    assign spi_ready = (cur_sta == ST_IDLE);

    //buffer refresh
    always @ (posedge clk or negedge RSTn) begin
        if(!RSTn) begin
            DATA_BUFFER <= 24'd0;
        end
        else if(spi_ready && tx_valid) begin
            DATA_BUFFER <= BUS_DATA;
        end
        else begin
            DATA_BUFFER <= DATA_BUFFER;
        end
    end

    //spi
    assign spi_cs = ~(cur_sta == ST_W);
    assign spi_data = ((cur_sta == ST_W) && (data_cnt <= 5'd23)) ? DATA_BUFFER[5'd23-data_cnt] : 1'b0;

    always @ (posedge clk or negedge RSTn) begin
        if(!RSTn) begin
            spi_clk <= 1'b0;
        end
        else if(cur_sta == ST_W) begin
            if(sclk_cnt == 5'd11) begin
                spi_clk <= 1'b1;
            end
            else if(sclk_cnt == 5'd23) begin
                spi_clk <= 1'b0;
            end
            else begin
                spi_clk <= spi_clk;
            end
        end
        else begin
            spi_clk <= 1'b0;
        end
    end

    //cnt
    always @ (posedge clk or negedge RSTn) begin
        if(!RSTn) begin
            sclk_cnt <= 5'd0;
        end
        else if(cur_sta == ST_W) begin
            sclk_cnt <=  (sclk_cnt == 5'd23) ? 5'd0 : sclk_cnt + 1'b1 ;
        end
        else if(cur_sta == ST_WAIT) begin
            sclk_cnt <=  sclk_cnt + 1'b1 ;
        end
        else begin
            sclk_cnt <= 5'd0;
        end
    end

    always @ (posedge clk or negedge RSTn) begin
        if(!RSTn) begin
            data_cnt <= 5'd0;
        end
        else if(cur_sta == ST_W) begin
            data_cnt <=  (sclk_cnt == 5'd23) ? data_cnt + 1'b1 : data_cnt ;
        end
        else begin
            data_cnt <= 5'd0;
        end
    end



    //FSM
    always @ (posedge clk or negedge RSTn) begin
        if(!RSTn) begin
            cur_sta <= ST_IDLE;
        end
        else begin
            cur_sta <= nxt_sta;
        end
    end

    always @ (*) begin
        case(cur_sta)
            ST_IDLE : begin
                nxt_sta = tx_valid ? ST_W :ST_IDLE;
            end
            ST_W    : begin
                nxt_sta =(data_cnt == 5'd24 && sclk_cnt == 5'd10) ? ST_WAIT :ST_W;
            end
            ST_WAIT : begin
                nxt_sta =(sclk_cnt == 5'd30) ? ST_IDLE : ST_WAIT ;
            end
            default : begin
                nxt_sta = ST_IDLE;
            end
        endcase
    end


endmodule

src/bus.v
module bus(
        input	wire	clk			,
        input	wire	RSTn		,

        input	wire[23:0]TOP_DATA	,
        input	wire	top_valid	,
        output	wire	bus_ready	,

        input	wire	spi_ready,
        output	wire	tx_valid,
        output	wire[23:0] BUS_DATA
    );
    reg  [23:0] DATA_BUFFER;
    reg data_status;

    //bus buffer refresh
    always @ (posedge clk or negedge RSTn) begin
        if (!RSTn) begin
            DATA_BUFFER <= 24'd0;
        end
        else if (top_valid && bus_ready)  begin
            DATA_BUFFER <= TOP_DATA;
        end
        else begin
            DATA_BUFFER <= DATA_BUFFER;
        end
    end

    //bus buffer status
    always @ (posedge clk or negedge RSTn) begin
        if(!RSTn) begin
            data_status <= 1'b0;
        end
        else begin
            case(data_status)
                1'b0 : begin
                    data_status <= top_valid ? 1'b1 :1'b0;
                end
                1'b1 : begin
                    data_status <= spi_ready ? (top_valid ? 1'b1 : 1'b0) : data_status;
                end
                default : begin
                    data_status <= data_status;
                end
            endcase
        end
    end

    //bus ready
    assign bus_ready = (!data_status) || spi_ready;

    //tx valid
    assign tx_valid = data_status;

    //BUS_DATA
    assign BUS_DATA = tx_valid ? DATA_BUFFER : 24'd0;


endmodule

src/top.v
module top(
        input	wire	clk			,
        input	wire	RSTn		,
        input   wire    top_valid   ,

        output	wire	spi_cs		,
        output	reg		spi_clk		,
        output	wire	spi_data
    );


    wire	bus_ready;

    reg [23:0] data_0;
    reg [23:0] data_1;
    reg [23:0] data_2;
    reg [23:0] data_3;

    always @ (posedge clk or negedge RSTn) begin
        if (!RSTn) begin
            data_0 <= 24'h28bb85;
            data_1 <= 24'h000fff;
            data_2 <= 24'h555555;
            data_3 <= 24'h123456;
        end
        else if (top_valid && bus_ready)  begin
            data_0 <= data_1;
            data_1 <= data_2;
            data_2 <= data_3;
            data_3 <= data_0;
        end
        else begin
            data_0 <= data_0;
            data_1 <= data_1;
            data_2 <= data_2;
            data_3 <= data_3;
        end
    end


    wire 	tx_valid;

    bus u_bus(
            //ports
            .clk       		( clk       		),
            .RSTn      		( RSTn      		),
            .TOP_DATA  		( data_0  	    	),
            .top_valid 		( top_valid 		),
            .bus_ready 		( bus_ready 		),
            .spi_ready 		( spi_ready 		),
            .tx_valid  		( tx_valid  		),
            .BUS_DATA  		( BUS_DATA  	    	)
        );

    wire 	spi_ready;
    wire [23:0] BUS_DATA;

    spi_tx u_spi_tx(
               //ports
               .clk       		( clk       		),
               .RSTn      		( RSTn      		),
               .BUS_DATA  		( BUS_DATA  		),
               .tx_valid  		( tx_valid  		),
               .spi_ready 		( spi_ready 		),
               .spi_cs    		( spi_cs    		),
               .spi_clk   		( spi_clk   		),
               .spi_data  		( spi_data  		)
           );


endmodule

sim/sim_tb.v
`timescale 1ns/100ps
`include "top.v"

module sim_tb();
    reg clk_50;
    reg RSTn;
    reg top_valid;



    wire 	spi_cs;
    wire 	spi_clk;
    wire 	spi_data;

    top u_top(
            //ports
            .clk       		( clk_50       		),
            .RSTn      		( RSTn      		),
            .top_valid 		( top_valid 		),
            .spi_cs    		( spi_cs    		),
            .spi_clk   		( spi_clk   		),
            .spi_data  		( spi_data  		)
        );


    always #10 clk_50 = ~clk_50;

    initial begin
        clk_50 = 1;
        RSTn = 0;
        #20 RSTn <= 1;
        top_valid = 0;

        #120 top_valid <= 1;
        #50000 $finish;
    end

    initial begin
        $dumpfile("wave.vcd");
        $dumpvars(0, sim_tb);
    end


endmodule

sim_result/wave.vcd
$date
	Mon Jun 13 15:58:16 2022
$end
$version
	Icarus Verilog
$end
$timescale
	100ps
$end
$scope module sim_tb $end
$var wire 1 ! spi_data $end
$var wire 1 " spi_cs $end
$var wire 1 # spi_clk $end
$var reg 1 $ RSTn $end
$var reg 1 % clk_50 $end
$var reg 1 & top_valid $end
$scope module u_top $end
$var wire 1 $ RSTn $end
$var wire 1 % clk $end
$var wire 1 & top_valid $end
$var wire 1 ' tx_valid $end
$var wire 1 ( spi_ready $end
$var wire 1 ! spi_data $end
$var wire 1 " spi_cs $end
$var wire 1 # spi_clk $end
$var wire 1 ) bus_ready $end
$var wire 24 * BUS_DATA [23:0] $end
$var reg 24 + data_0 [23:0] $end
$var reg 24 , data_1 [23:0] $end
$var reg 24 - data_2 [23:0] $end
$var reg 24 . data_3 [23:0] $end
$scope module u_bus $end
$var wire 1 $ RSTn $end
$var wire 24 / TOP_DATA [23:0] $end
$var wire 1 ) bus_ready $end
$var wire 1 % clk $end
$var wire 1 & top_valid $end
$var wire 1 ' tx_valid $end
$var wire 1 ( spi_ready $end
$var wire 24 0 BUS_DATA [23:0] $end
$var reg 24 1 DATA_BUFFER [23:0] $end
$var reg 1 2 data_status $end
$upscope $end
$scope module u_spi_tx $end
$var wire 24 3 BUS_DATA [23:0] $end
$var wire 1 $ RSTn $end
$var wire 1 % clk $end
$var wire 1 " spi_cs $end
$var wire 1 ' tx_valid $end
$var wire 1 ( spi_ready $end
$var wire 1 ! spi_data $end
$var reg 24 4 DATA_BUFFER [23:0] $end
$var reg 2 5 cur_sta [1:0] $end
$var reg 5 6 data_cnt [4:0] $end
$var reg 2 7 nxt_sta [1:0] $end
$var reg 5 8 sclk_cnt [4:0] $end
$var reg 1 # spi_clk $end
$upscope $end
$upscope $end
$upscope $end
$enddefinitions $end
#0
$dumpvars
b0 8
b0 7
b0 6
b0 5
b0 4
b0 3
02
b0 1
b0 0
b1010001011101110000101 /
b100100011010001010110 .
b10101010101010101010101 -
b111111111111 ,
b1010001011101110000101 +
b0 *
1)
1(
0'
x&
1%
0$
0#
1"
0!
$end
#100
0%
#200
1$
1%
0&
#300
0%
#400
1%
#500
0%
#600
1%
#700
0%
#800
1%
#900
0%
#1000
1%
#1100
0%
#1200
1%
#1300
0%
#1400
1&
1%
#1500
0%
#1600
b1010001011101110000101 *
b1010001011101110000101 0
b1010001011101110000101 3
b1 7
b1010001011101110000101 1
1'
12
b1010001011101110000101 .
b100100011010001010110 -
b10101010101010101010101 ,
b111111111111 +
b111111111111 /
1%
#1700
0%
#1800
0)
0"
b111111111111 *
b111111111111 0
b111111111111 3
b111111111111 .
b1010001011101110000101 -
b100100011010001010110 ,
b10101010101010101010101 +
b10101010101010101010101 /
0(
b1 5
b1010001011101110000101 4
b111111111111 1
1%
#1900
0%
#2000
b1 8
1%
#2100
0%
#2200
b10 8
1%
#2300
0%
#2400
b11 8
1%
#2500
0%
#2600
b100 8
1%
#2700
0%
#2800
b101 8
1%
#2900
0%
#3000
b110 8
1%
#3100
0%
#3200
b111 8
1%
#3300
0%
#3400
b1000 8
1%
#3500
0%
#3600
b1001 8
1%
#3700
0%
#3800
b1010 8
1%
#3900
0%
#4000
b1011 8
1%
#4100
0%
#4200
b1100 8
1#
1%
#4300
0%
#4400
b1101 8
1%
#4500
0%
#4600
b1110 8
1%
#4700
0%
#4800
b1111 8
1%
#4900
0%
#5000
b10000 8
1%
#5100
0%
#5200
b10001 8
1%
#5300
0%
#5400
b10010 8
1%
#5500
0%
#5600
b10011 8
1%
#5700
0%
#5800
b10100 8
1%
#5900
0%
#6000
b10101 8
1%
#6100
0%
#6200
b10110 8
1%
#6300
0%
#6400
b10111 8
1%
#6500
0%
#6600
b1 6
b0 8
0#
1%
#6700
0%
#6800
b1 8
1%
#6900
0%
#7000
b10 8
1%
#7100
0%
#7200
b11 8
1%
#7300
0%
#7400
b100 8
1%
#7500
0%
#7600
b101 8
1%
#7700
0%
#7800
b110 8
1%
#7900
0%
#8000
b111 8
1%
#8100
0%
#8200
b1000 8
1%
#8300
0%
#8400
b1001 8
1%
#8500
0%
#8600
b1010 8
1%
#8700
0%
#8800
b1011 8
1%
#8900
0%
#9000
b1100 8
1#
1%
#9100
0%
#9200
b1101 8
1%
#9300
0%
#9400
b1110 8
1%
#9500
0%
#9600
b1111 8
1%
#9700
0%
#9800
b10000 8
1%
#9900
0%
#10000
b10001 8
1%
#10100
0%
#10200
b10010 8
1%
#10300
0%
#10400
b10011 8
1%
#10500
0%
#10600
b10100 8
1%
#10700
0%
#10800
b10101 8
1%
#10900
0%
#11000
b10110 8
1%
#11100
0%
#11200
b10111 8
1%
#11300
0%
#11400
1!
b10 6
b0 8
0#
1%
#11500
0%
#11600
b1 8
1%
#11700
0%
#11800
b10 8
1%
#11900
0%
#12000
b11 8
1%
#12100
0%
#12200
b100 8
1%
#12300
0%
#12400
b101 8
1%
#12500
0%
#12600
b110 8
1%
#12700
0%
#12800
b111 8
1%
#12900
0%
#13000
b1000 8
1%
#13100
0%
#13200
b1001 8
1%
#13300
0%
#13400
b1010 8
1%
#13500
0%
#13600
b1011 8
1%
#13700
0%
#13800
b1100 8
1#
1%
#13900
0%
#14000
b1101 8
1%
#14100
0%
#14200
b1110 8
1%
#14300
0%
#14400
b1111 8
1%
#14500
0%
#14600
b10000 8
1%
#14700
0%
#14800
b10001 8
1%
#14900
0%
#15000
b10010 8
1%
#15100
0%
#15200
b10011 8
1%
#15300
0%
#15400
b10100 8
1%
#15500
0%
#15600
b10101 8
1%
#15700
0%
#15800
b10110 8
1%
#15900
0%
#16000
b10111 8
1%
#16100
0%
#16200
0!
b11 6
b0 8
0#
1%
#16300
0%
#16400
b1 8
1%
#16500
0%
#16600
b10 8
1%
#16700
0%
#16800
b11 8
1%
#16900
0%
#17000
b100 8
1%
#17100
0%
#17200
b101 8
1%
#17300
0%
#17400
b110 8
1%
#17500
0%
#17600
b111 8
1%
#17700
0%
#17800
b1000 8
1%
#17900
0%
#18000
b1001 8
1%
#18100
0%
#18200
b1010 8
1%
#18300
0%
#18400
b1011 8
1%
#18500
0%
#18600
b1100 8
1#
1%
#18700
0%
#18800
b1101 8
1%
#18900
0%
#19000
b1110 8
1%
#19100
0%
#19200
b1111 8
1%
#19300
0%
#19400
b10000 8
1%
#19500
0%
#19600
b10001 8
1%
#19700
0%
#19800
b10010 8
1%
#19900
0%
#20000
b10011 8
1%
#20100
0%
#20200
b10100 8
1%
#20300
0%
#20400
b10101 8
1%
#20500
0%
#20600
b10110 8
1%
#20700
0%
#20800
b10111 8
1%
#20900
0%
#21000
1!
b100 6
b0 8
0#
1%
#21100
0%
#21200
b1 8
1%
#21300
0%
#21400
b10 8
1%
#21500
0%
#21600
b11 8
1%
#21700
0%
#21800
b100 8
1%
#21900
0%
#22000
b101 8
1%
#22100
0%
#22200
b110 8
1%
#22300
0%
#22400
b111 8
1%
#22500
0%
#22600
b1000 8
1%
#22700
0%
#22800
b1001 8
1%
#22900
0%
#23000
b1010 8
1%
#23100
0%
#23200
b1011 8
1%
#23300
0%
#23400
b1100 8
1#
1%
#23500
0%
#23600
b1101 8
1%
#23700
0%
#23800
b1110 8
1%
#23900
0%
#24000
b1111 8
1%
#24100
0%
#24200
b10000 8
1%
#24300
0%
#24400
b10001 8
1%
#24500
0%
#24600
b10010 8
1%
#24700
0%
#24800
b10011 8
1%
#24900
0%
#25000
b10100 8
1%
#25100
0%
#25200
b10101 8
1%
#25300
0%
#25400
b10110 8
1%
#25500
0%
#25600
b10111 8
1%
#25700
0%
#25800
0!
b101 6
b0 8
0#
1%
#25900
0%
#26000
b1 8
1%
#26100
0%
#26200
b10 8
1%
#26300
0%
#26400
b11 8
1%
#26500
0%
#26600
b100 8
1%
#26700
0%
#26800
b101 8
1%
#26900
0%
#27000
b110 8
1%
#27100
0%
#27200
b111 8
1%
#27300
0%
#27400
b1000 8
1%
#27500
0%
#27600
b1001 8
1%
#27700
0%
#27800
b1010 8
1%
#27900
0%
#28000
b1011 8
1%
#28100
0%
#28200
b1100 8
1#
1%
#28300
0%
#28400
b1101 8
1%
#28500
0%
#28600
b1110 8
1%
#28700
0%
#28800
b1111 8
1%
#28900
0%
#29000
b10000 8
1%
#29100
0%
#29200
b10001 8
1%
#29300
0%
#29400
b10010 8
1%
#29500
0%
#29600
b10011 8
1%
#29700
0%
#29800
b10100 8
1%
#29900
0%
#30000
b10101 8
1%
#30100
0%
#30200
b10110 8
1%
#30300
0%
#30400
b10111 8
1%
#30500
0%
#30600
b110 6
b0 8
0#
1%
#30700
0%
#30800
b1 8
1%
#30900
0%
#31000
b10 8
1%
#31100
0%
#31200
b11 8
1%
#31300
0%
#31400
b100 8
1%
#31500
0%
#31600
b101 8
1%
#31700
0%
#31800
b110 8
1%
#31900
0%
#32000
b111 8
1%
#32100
0%
#32200
b1000 8
1%
#32300
0%
#32400
b1001 8
1%
#32500
0%
#32600
b1010 8
1%
#32700
0%
#32800
b1011 8
1%
#32900
0%
#33000
b1100 8
1#
1%
#33100
0%
#33200
b1101 8
1%
#33300
0%
#33400
b1110 8
1%
#33500
0%
#33600
b1111 8
1%
#33700
0%
#33800
b10000 8
1%
#33900
0%
#34000
b10001 8
1%
#34100
0%
#34200
b10010 8
1%
#34300
0%
#34400
b10011 8
1%
#34500
0%
#34600
b10100 8
1%
#34700
0%
#34800
b10101 8
1%
#34900
0%
#35000
b10110 8
1%
#35100
0%
#35200
b10111 8
1%
#35300
0%
#35400
b111 6
b0 8
0#
1%
#35500
0%
#35600
b1 8
1%
#35700
0%
#35800
b10 8
1%
#35900
0%
#36000
b11 8
1%
#36100
0%
#36200
b100 8
1%
#36300
0%
#36400
b101 8
1%
#36500
0%
#36600
b110 8
1%
#36700
0%
#36800
b111 8
1%
#36900
0%
#37000
b1000 8
1%
#37100
0%
#37200
b1001 8
1%
#37300
0%
#37400
b1010 8
1%
#37500
0%
#37600
b1011 8
1%
#37700
0%
#37800
b1100 8
1#
1%
#37900
0%
#38000
b1101 8
1%
#38100
0%
#38200
b1110 8
1%
#38300
0%
#38400
b1111 8
1%
#38500
0%
#38600
b10000 8
1%
#38700
0%
#38800
b10001 8
1%
#38900
0%
#39000
b10010 8
1%
#39100
0%
#39200
b10011 8
1%
#39300
0%
#39400
b10100 8
1%
#39500
0%
#39600
b10101 8
1%
#39700
0%
#39800
b10110 8
1%
#39900
0%
#40000
b10111 8
1%
#40100
0%
#40200
1!
b1000 6
b0 8
0#
1%
#40300
0%
#40400
b1 8
1%
#40500
0%
#40600
b10 8
1%
#40700
0%
#40800
b11 8
1%
#40900
0%
#41000
b100 8
1%
#41100
0%
#41200
b101 8
1%
#41300
0%
#41400
b110 8
1%
#41500
0%
#41600
b111 8
1%
#41700
0%
#41800
b1000 8
1%
#41900
0%
#42000
b1001 8
1%
#42100
0%
#42200
b1010 8
1%
#42300
0%
#42400
b1011 8
1%
#42500
0%
#42600
b1100 8
1#
1%
#42700
0%
#42800
b1101 8
1%
#42900
0%
#43000
b1110 8
1%
#43100
0%
#43200
b1111 8
1%
#43300
0%
#43400
b10000 8
1%
#43500
0%
#43600
b10001 8
1%
#43700
0%
#43800
b10010 8
1%
#43900
0%
#44000
b10011 8
1%
#44100
0%
#44200
b10100 8
1%
#44300
0%
#44400
b10101 8
1%
#44500
0%
#44600
b10110 8
1%
#44700
0%
#44800
b10111 8
1%
#44900
0%
#45000
0!
b1001 6
b0 8
0#
1%
#45100
0%
#45200
b1 8
1%
#45300
0%
#45400
b10 8
1%
#45500
0%
#45600
b11 8
1%
#45700
0%
#45800
b100 8
1%
#45900
0%
#46000
b101 8
1%
#46100
0%
#46200
b110 8
1%
#46300
0%
#46400
b111 8
1%
#46500
0%
#46600
b1000 8
1%
#46700
0%
#46800
b1001 8
1%
#46900
0%
#47000
b1010 8
1%
#47100
0%
#47200
b1011 8
1%
#47300
0%
#47400
b1100 8
1#
1%
#47500
0%
#47600
b1101 8
1%
#47700
0%
#47800
b1110 8
1%
#47900
0%
#48000
b1111 8
1%
#48100
0%
#48200
b10000 8
1%
#48300
0%
#48400
b10001 8
1%
#48500
0%
#48600
b10010 8
1%
#48700
0%
#48800
b10011 8
1%
#48900
0%
#49000
b10100 8
1%
#49100
0%
#49200
b10101 8
1%
#49300
0%
#49400
b10110 8
1%
#49500
0%
#49600
b10111 8
1%
#49700
0%
#49800
1!
b1010 6
b0 8
0#
1%
#49900
0%
#50000
b1 8
1%
#50100
0%
#50200
b10 8
1%
#50300
0%
#50400
b11 8
1%
#50500
0%
#50600
b100 8
1%
#50700
0%
#50800
b101 8
1%
#50900
0%
#51000
b110 8
1%
#51100
0%
#51200
b111 8
1%
#51300
0%
#51400
b1000 8
1%
#51500
0%
#51600
b1001 8
1%
#51700
0%
#51800
b1010 8
1%
#51900
0%
#52000
b1011 8
1%
#52100
0%
#52200
b1100 8
1#
1%
#52300
0%
#52400
b1101 8
1%
#52500
0%
#52600
b1110 8
1%
#52700
0%
#52800
b1111 8
1%
#52900
0%
#53000
b10000 8
1%
#53100
0%
#53200
b10001 8
1%
#53300
0%
#53400
b10010 8
1%
#53500
0%
#53600
b10011 8
1%
#53700
0%
#53800
b10100 8
1%
#53900
0%
#54000
b10101 8
1%
#54100
0%
#54200
b10110 8
1%
#54300
0%
#54400
b10111 8
1%
#54500
0%
#54600
b1011 6
b0 8
0#
1%
#54700
0%
#54800
b1 8
1%
#54900
0%
#55000
b10 8
1%
#55100
0%
#55200
b11 8
1%
#55300
0%
#55400
b100 8
1%
#55500
0%
#55600
b101 8
1%
#55700
0%
#55800
b110 8
1%
#55900
0%
#56000
b111 8
1%
#56100
0%
#56200
b1000 8
1%
#56300
0%
#56400
b1001 8
1%
#56500
0%
#56600
b1010 8
1%
#56700
0%
#56800
b1011 8
1%
#56900
0%
#57000
b1100 8
1#
1%
#57100
0%
#57200
b1101 8
1%
#57300
0%
#57400
b1110 8
1%
#57500
0%
#57600
b1111 8
1%
#57700
0%
#57800
b10000 8
1%
#57900
0%
#58000
b10001 8
1%
#58100
0%
#58200
b10010 8
1%
#58300
0%
#58400
b10011 8
1%
#58500
0%
#58600
b10100 8
1%
#58700
0%
#58800
b10101 8
1%
#58900
0%
#59000
b10110 8
1%
#59100
0%
#59200
b10111 8
1%
#59300
0%
#59400
b1100 6
b0 8
0#
1%
#59500
0%
#59600
b1 8
1%
#59700
0%
#59800
b10 8
1%
#59900
0%
#60000
b11 8
1%
#60100
0%
#60200
b100 8
1%
#60300
0%
#60400
b101 8
1%
#60500
0%
#60600
b110 8
1%
#60700
0%
#60800
b111 8
1%
#60900
0%
#61000
b1000 8
1%
#61100
0%
#61200
b1001 8
1%
#61300
0%
#61400
b1010 8
1%
#61500
0%
#61600
b1011 8
1%
#61700
0%
#61800
b1100 8
1#
1%
#61900
0%
#62000
b1101 8
1%
#62100
0%
#62200
b1110 8
1%
#62300
0%
#62400
b1111 8
1%
#62500
0%
#62600
b10000 8
1%
#62700
0%
#62800
b10001 8
1%
#62900
0%
#63000
b10010 8
1%
#63100
0%
#63200
b10011 8
1%
#63300
0%
#63400
b10100 8
1%
#63500
0%
#63600
b10101 8
1%
#63700
0%
#63800
b10110 8
1%
#63900
0%
#64000
b10111 8
1%
#64100
0%
#64200
0!
b1101 6
b0 8
0#
1%
#64300
0%
#64400
b1 8
1%
#64500
0%
#64600
b10 8
1%
#64700
0%
#64800
b11 8
1%
#64900
0%
#65000
b100 8
1%
#65100
0%
#65200
b101 8
1%
#65300
0%
#65400
b110 8
1%
#65500
0%
#65600
b111 8
1%
#65700
0%
#65800
b1000 8
1%
#65900
0%
#66000
b1001 8
1%
#66100
0%
#66200
b1010 8
1%
#66300
0%
#66400
b1011 8
1%
#66500
0%
#66600
b1100 8
1#
1%
#66700
0%
#66800
b1101 8
1%
#66900
0%
#67000
b1110 8
1%
#67100
0%
#67200
b1111 8
1%
#67300
0%
#67400
b10000 8
1%
#67500
0%
#67600
b10001 8
1%
#67700
0%
#67800
b10010 8
1%
#67900
0%
#68000
b10011 8
1%
#68100
0%
#68200
b10100 8
1%
#68300
0%
#68400
b10101 8
1%
#68500
0%
#68600
b10110 8
1%
#68700
0%
#68800
b10111 8
1%
#68900
0%
#69000
1!
b1110 6
b0 8
0#
1%
#69100
0%
#69200
b1 8
1%
#69300
0%
#69400
b10 8
1%
#69500
0%
#69600
b11 8
1%
#69700
0%
#69800
b100 8
1%
#69900
0%
#70000
b101 8
1%
#70100
0%
#70200
b110 8
1%
#70300
0%
#70400
b111 8
1%
#70500
0%
#70600
b1000 8
1%
#70700
0%
#70800
b1001 8
1%
#70900
0%
#71000
b1010 8
1%
#71100
0%
#71200
b1011 8
1%
#71300
0%
#71400
b1100 8
1#
1%
#71500
0%
#71600
b1101 8
1%
#71700
0%
#71800
b1110 8
1%
#71900
0%
#72000
b1111 8
1%
#72100
0%
#72200
b10000 8
1%
#72300
0%
#72400
b10001 8
1%
#72500
0%
#72600
b10010 8
1%
#72700
0%
#72800
b10011 8
1%
#72900
0%
#73000
b10100 8
1%
#73100
0%
#73200
b10101 8
1%
#73300
0%
#73400
b10110 8
1%
#73500
0%
#73600
b10111 8
1%
#73700
0%
#73800
b1111 6
b0 8
0#
1%
#73900
0%
#74000
b1 8
1%
#74100
0%
#74200
b10 8
1%
#74300
0%
#74400
b11 8
1%
#74500
0%
#74600
b100 8
1%
#74700
0%
#74800
b101 8
1%
#74900
0%
#75000
b110 8
1%
#75100
0%
#75200
b111 8
1%
#75300
0%
#75400
b1000 8
1%
#75500
0%
#75600
b1001 8
1%
#75700
0%
#75800
b1010 8
1%
#75900
0%
#76000
b1011 8
1%
#76100
0%
#76200
b1100 8
1#
1%
#76300
0%
#76400
b1101 8
1%
#76500
0%
#76600
b1110 8
1%
#76700
0%
#76800
b1111 8
1%
#76900
0%
#77000
b10000 8
1%
#77100
0%
#77200
b10001 8
1%
#77300
0%
#77400
b10010 8
1%
#77500
0%
#77600
b10011 8
1%
#77700
0%
#77800
b10100 8
1%
#77900
0%
#78000
b10101 8
1%
#78100
0%
#78200
b10110 8
1%
#78300
0%
#78400
b10111 8
1%
#78500
0%
#78600
b10000 6
b0 8
0#
1%
#78700
0%
#78800
b1 8
1%
#78900
0%
#79000
b10 8
1%
#79100
0%
#79200
b11 8
1%
#79300
0%
#79400
b100 8
1%
#79500
0%
#79600
b101 8
1%
#79700
0%
#79800
b110 8
1%
#79900
0%
#80000
b111 8
1%
#80100
0%
#80200
b1000 8
1%
#80300
0%
#80400
b1001 8
1%
#80500
0%
#80600
b1010 8
1%
#80700
0%
#80800
b1011 8
1%
#80900
0%
#81000
b1100 8
1#
1%
#81100
0%
#81200
b1101 8
1%
#81300
0%
#81400
b1110 8
1%
#81500
0%
#81600
b1111 8
1%
#81700
0%
#81800
b10000 8
1%
#81900
0%
#82000
b10001 8
1%
#82100
0%
#82200
b10010 8
1%
#82300
0%
#82400
b10011 8
1%
#82500
0%
#82600
b10100 8
1%
#82700
0%
#82800
b10101 8
1%
#82900
0%
#83000
b10110 8
1%
#83100
0%
#83200
b10111 8
1%
#83300
0%
#83400
0!
b10001 6
b0 8
0#
1%
#83500
0%
#83600
b1 8
1%
#83700
0%
#83800
b10 8
1%
#83900
0%
#84000
b11 8
1%
#84100
0%
#84200
b100 8
1%
#84300
0%
#84400
b101 8
1%
#84500
0%
#84600
b110 8
1%
#84700
0%
#84800
b111 8
1%
#84900
0%
#85000
b1000 8
1%
#85100
0%
#85200
b1001 8
1%
#85300
0%
#85400
b1010 8
1%
#85500
0%
#85600
b1011 8
1%
#85700
0%
#85800
b1100 8
1#
1%
#85900
0%
#86000
b1101 8
1%
#86100
0%
#86200
b1110 8
1%
#86300
0%
#86400
b1111 8
1%
#86500
0%
#86600
b10000 8
1%
#86700
0%
#86800
b10001 8
1%
#86900
0%
#87000
b10010 8
1%
#87100
0%
#87200
b10011 8
1%
#87300
0%
#87400
b10100 8
1%
#87500
0%
#87600
b10101 8
1%
#87700
0%
#87800
b10110 8
1%
#87900
0%
#88000
b10111 8
1%
#88100
0%
#88200
b10010 6
b0 8
0#
1%
#88300
0%
#88400
b1 8
1%
#88500
0%
#88600
b10 8
1%
#88700
0%
#88800
b11 8
1%
#88900
0%
#89000
b100 8
1%
#89100
0%
#89200
b101 8
1%
#89300
0%
#89400
b110 8
1%
#89500
0%
#89600
b111 8
1%
#89700
0%
#89800
b1000 8
1%
#89900
0%
#90000
b1001 8
1%
#90100
0%
#90200
b1010 8
1%
#90300
0%
#90400
b1011 8
1%
#90500
0%
#90600
b1100 8
1#
1%
#90700
0%
#90800
b1101 8
1%
#90900
0%
#91000
b1110 8
1%
#91100
0%
#91200
b1111 8
1%
#91300
0%
#91400
b10000 8
1%
#91500
0%
#91600
b10001 8
1%
#91700
0%
#91800
b10010 8
1%
#91900
0%
#92000
b10011 8
1%
#92100
0%
#92200
b10100 8
1%
#92300
0%
#92400
b10101 8
1%
#92500
0%
#92600
b10110 8
1%
#92700
0%
#92800
b10111 8
1%
#92900
0%
#93000
b10011 6
b0 8
0#
1%
#93100
0%
#93200
b1 8
1%
#93300
0%
#93400
b10 8
1%
#93500
0%
#93600
b11 8
1%
#93700
0%
#93800
b100 8
1%
#93900
0%
#94000
b101 8
1%
#94100
0%
#94200
b110 8
1%
#94300
0%
#94400
b111 8
1%
#94500
0%
#94600
b1000 8
1%
#94700
0%
#94800
b1001 8
1%
#94900
0%
#95000
b1010 8
1%
#95100
0%
#95200
b1011 8
1%
#95300
0%
#95400
b1100 8
1#
1%
#95500
0%
#95600
b1101 8
1%
#95700
0%
#95800
b1110 8
1%
#95900
0%
#96000
b1111 8
1%
#96100
0%
#96200
b10000 8
1%
#96300
0%
#96400
b10001 8
1%
#96500
0%
#96600
b10010 8
1%
#96700
0%
#96800
b10011 8
1%
#96900
0%
#97000
b10100 8
1%
#97100
0%
#97200
b10101 8
1%
#97300
0%
#97400
b10110 8
1%
#97500
0%
#97600
b10111 8
1%
#97700
0%
#97800
b10100 6
b0 8
0#
1%
#97900
0%
#98000
b1 8
1%
#98100
0%
#98200
b10 8
1%
#98300
0%
#98400
b11 8
1%
#98500
0%
#98600
b100 8
1%
#98700
0%
#98800
b101 8
1%
#98900
0%
#99000
b110 8
1%
#99100
0%
#99200
b111 8
1%
#99300
0%
#99400
b1000 8
1%
#99500
0%
#99600
b1001 8
1%
#99700
0%
#99800
b1010 8
1%
#99900
0%
#100000
b1011 8
1%
#100100
0%
#100200
b1100 8
1#
1%
#100300
0%
#100400
b1101 8
1%
#100500
0%
#100600
b1110 8
1%
#100700
0%
#100800
b1111 8
1%
#100900
0%
#101000
b10000 8
1%
#101100
0%
#101200
b10001 8
1%
#101300
0%
#101400
b10010 8
1%
#101500
0%
#101600
b10011 8
1%
#101700
0%
#101800
b10100 8
1%
#101900
0%
#102000
b10101 8
1%
#102100
0%
#102200
b10110 8
1%
#102300
0%
#102400
b10111 8
1%
#102500
0%
#102600
1!
b10101 6
b0 8
0#
1%
#102700
0%
#102800
b1 8
1%
#102900
0%
#103000
b10 8
1%
#103100
0%
#103200
b11 8
1%
#103300
0%
#103400
b100 8
1%
#103500
0%
#103600
b101 8
1%
#103700
0%
#103800
b110 8
1%
#103900
0%
#104000
b111 8
1%
#104100
0%
#104200
b1000 8
1%
#104300
0%
#104400
b1001 8
1%
