src/bus.v
module bus(
        input	wire	clk			    ,
        input	wire	RSTn		    ,

        input	wire[23:0]master_data   ,
        input	wire	master_valid    ,
        output	wire	bus_ready	    ,

        input	wire	slave_ready     ,
        output	wire	bus_valid       ,
        output	wire[23:0] bus_data
    );

    reg  [23:0] DATA_BUFFER;
    reg buffer_full;
    reg slave_ready_d1;

    always @(posedge clk or negedge RSTn) begin
        if (!RSTn) begin
            slave_ready_d1 <= 1'd0;
        end
        else begin
            slave_ready_d1 <= slave_ready;
        end
    end

    //bus buffer refresh
    always @ (posedge clk or negedge RSTn) begin
        if (!RSTn) begin
            DATA_BUFFER <= 24'd0;
        end
        else if (master_valid && bus_ready && (!slave_ready) && (!buffer_full)) begin
            DATA_BUFFER <= master_data;
        end
        else begin
            DATA_BUFFER <= DATA_BUFFER;
        end
    end

    //bus buffer status
    always @(posedge clk or negedge RSTn) begin
        if (!RSTn)
            buffer_full <= 1'd0;
        else if (master_valid && (!slave_ready) && (!buffer_full))
            buffer_full <= 1'd1;
        else if (slave_ready == 1'd1)
            buffer_full <= 1'd0;
    end

    //bus ready
    assign bus_ready = (!buffer_full) || slave_ready_d1;

    //tx valid
    assign bus_valid = buffer_full || master_valid;

    //BUS_DATA
    assign bus_data = buffer_full ? DATA_BUFFER : master_data;


endmodule

sim/sim_tb.v
`timescale 1ns/100ps
`include "../src/bus.v"
module sim_tb();
    reg clk_50;
    reg RSTn;

    reg 	bus_ready;
    reg 	bus_valid;
    reg [23:0]	bus_data;

    reg 	slave_ready;
    reg 	master_valid;
    reg [23:0] master_data;

    bus u_bus(
            //ports
            .clk          		( clk_50          	),
            .RSTn         		( RSTn         		),
            .master_data  		( dut_master_data  	),
            .master_valid 		( dut_master_valid 	),
            .bus_ready    		( bus_ready    		),
            .slave_ready  		( dut_slave_ready  	),
            .bus_valid    		( bus_valid    		),
            .bus_data     		( bus_data     		)
        );

    wire [23:0]dut_bus_data;
    wire dut_bus_valid;
    wire dut_bus_ready;

    wire [23:0]dut_master_data;
    wire dut_master_valid;
    wire dut_slave_ready;

    assign #0.1 dut_bus_valid = bus_valid;
    assign #0.1 dut_bus_data = bus_data;
    assign #0.1 dut_bus_ready = bus_ready;

    assign #0.1 dut_master_valid = master_valid;
    assign #0.1 dut_master_data = master_data;
    assign #0.1 dut_slave_ready = slave_ready; 


    always #10 clk_50 = ~clk_50;

    initial begin
        clk_50 = 1;
        RSTn = 0;
        master_valid = 1'b0;
        master_data = 24'b0;
        slave_ready = 1'b0;
 
        #20 RSTn = 1;
        master_data = 24'hFFF000;
        master_valid = 1'b1;        
        slave_ready = 1'b1;
        #20  master_data = 24'h000FFF;
        #20  master_data = 24'h555555;
        #20  slave_ready = 1'b0;
        master_data = 24'h777777;
        #20  slave_ready = 1'b1;
        master_valid = 0;
        master_data = 24'h0;
        #20  slave_ready = 1'b0;
        #40
        slave_ready = 1;
        #20
        master_data = 24'h111111;
        master_valid = 1'b1; 
        #20
        master_data = 24'h222222;
        #20
        master_data = 24'h333333;
        master_valid = 0;
        #20 master_data = 24'h444444;
        #20 master_valid = 1; 
        master_data = 24'h112233;
        #20  master_data = 24'h223344;
        #20  slave_ready = 1'b0;
        master_data = 24'h445566;
        #20  slave_ready = 1'b1;
        master_valid = 0;
        master_data = 24'h667788;
        #20  slave_ready = 1'b0;

        
        #50000 $finish;
    end

    initial begin
        $dumpfile("./sim_result/wave.vcd");
        $dumpvars(0, sim_tb);
    end


endmodule

sim_result/wave.vcd
$date
	Wed Jun 15 17:42:48 2022
$end
$version
	Icarus Verilog
$end
$timescale
	100ps
$end
$scope module sim_tb $end
$var wire 24 ! dut_bus_data [23:0] $end
$var wire 1 " dut_bus_ready $end
$var wire 1 # dut_bus_valid $end
$var wire 24 $ dut_master_data [23:0] $end
$var wire 1 % dut_master_valid $end
$var wire 1 & dut_slave_ready $end
$var wire 1 ' bus_valid $end
$var wire 1 ( bus_ready $end
$var wire 24 ) bus_data [23:0] $end
$var reg 1 * RSTn $end
$var reg 1 + clk_50 $end
$var reg 24 , master_data [23:0] $end
$var reg 1 - master_valid $end
$var reg 1 . slave_ready $end
$scope module u_bus $end
$var wire 1 * RSTn $end
$var wire 1 ( bus_ready $end
$var wire 1 ' bus_valid $end
$var wire 1 + clk $end
$var wire 24 / master_data [23:0] $end
$var wire 1 % master_valid $end
$var wire 1 & slave_ready $end
$var wire 24 0 bus_data [23:0] $end
$var reg 24 1 DATA_BUFFER [23:0] $end
$var reg 1 2 buffer_full $end
$var reg 1 3 slave_ready_d1 $end
$upscope $end
$upscope $end
$enddefinitions $end
#0
$dumpvars
03
02
b0 1
bx 0
bx /
0.
0-
b0 ,
1+
0*
bx )
1(
x'
x&
x%
bx $
x#
x"
bx !
$end
#1
b0 )
b0 0
0'
1"
0&
b0 $
b0 /
0%
#2
b0 !
0#
#100
0+
#200
1+
1.
1-
b111111111111000000000000 ,
1*
#201
1'
b111111111111000000000000 )
b111111111111000000000000 0
1&
1%
b111111111111000000000000 $
b111111111111000000000000 /
#202
1#
b111111111111000000000000 !
#300
0+
#400
13
1+
b111111111111 ,
#401
b111111111111 )
b111111111111 0
b111111111111 $
b111111111111 /
#402
b111111111111 !
#500
0+
#600
1+
b10101010101010101010101 ,
#601
b10101010101010101010101 )
b10101010101010101010101 0
b10101010101010101010101 $
b10101010101010101010101 /
#602
b10101010101010101010101 !
#700
0+
#800
1+
b11101110111011101110111 ,
0.
#801
b11101110111011101110111 )
b11101110111011101110111 0
b11101110111011101110111 $
b11101110111011101110111 /
0&
#802
b11101110111011101110111 !
#900
0+
#1000
0(
12
b11101110111011101110111 1
03
1+
b0 ,
0-
1.
#1001
0"
b0 $
b0 /
0%
1&
#1100
0+
#1200
1(
b0 )
b0 0
0'
13
02
1+
0.
#1201
1"
b0 !
0#
0&
#1300
0+
#1400
03
1+
#1500
0+
#1600
1+
1.
#1601
1&
#1700
0+
#1800
13
1+
1-
b100010001000100010001 ,
#1801
1'
b100010001000100010001 )
b100010001000100010001 0
1%
b100010001000100010001 $
b100010001000100010001 /
#1802
1#
b100010001000100010001 !
#1900
0+
#2000
1+
b1000100010001000100010 ,
#2001
b1000100010001000100010 )
b1000100010001000100010 0
b1000100010001000100010 $
b1000100010001000100010 /
#2002
b1000100010001000100010 !
#2100
0+
#2200
1+
0-
b1100110011001100110011 ,
#2201
0'
b1100110011001100110011 )
b1100110011001100110011 0
0%
b1100110011001100110011 $
b1100110011001100110011 /
#2202
0#
b1100110011001100110011 !
#2300
0+
#2400
1+
b10001000100010001000100 ,
#2401
b10001000100010001000100 )
b10001000100010001000100 0
b10001000100010001000100 $
b10001000100010001000100 /
#2402
b10001000100010001000100 !
#2500
0+
#2600
1+
b100010010001000110011 ,
1-
#2601
b100010010001000110011 )
b100010010001000110011 0
1'
b100010010001000110011 $
b100010010001000110011 /
1%
#2602
b100010010001000110011 !
1#
#2700
0+
#2800
1+
b1000100011001101000100 ,
#2801
b1000100011001101000100 )
b1000100011001101000100 0
b1000100011001101000100 $
b1000100011001101000100 /
#2802
b1000100011001101000100 !
#2900
0+
#3000
1+
b10001000101010101100110 ,
0.
#3001
b10001000101010101100110 )
b10001000101010101100110 0
b10001000101010101100110 $
b10001000101010101100110 /
0&
#3002
b10001000101010101100110 !
#3100
0+
#3200
0(
03
b10001000101010101100110 1
12
1+
b11001100111011110001000 ,
0-
1.
#3201
0"
b11001100111011110001000 $
b11001100111011110001000 /
0%
1&
#3300
0+
#3400
b11001100111011110001000 )
b11001100111011110001000 0
0'
1(
02
13
1+
0.
#3401
b11001100111011110001000 !
0#
1"
0&
#3500
0+
#3600
03
1+
